AUTHORS.rst
HISTORY.rst
LICENSE
MANIFEST.in
setup.cfg
setup.py
django_session_log.egg-info/PKG-INFO
django_session_log.egg-info/SOURCES.txt
django_session_log.egg-info/dependency_links.txt
django_session_log.egg-info/not-zip-safe
django_session_log.egg-info/requires.txt
django_session_log.egg-info/top_level.txt
session_log/__init__.py
session_log/activity.py
session_log/admin.py
session_log/compat.py
session_log/conf.py
session_log/middleware.py
session_log/models.py
session_log/urls.py
session_log/utils.py
session_log/views.py
session_log/migrations/0001_initial.py
session_log/migrations/__init__.py
session_log/templates/session_activity/session_list.html